lms_prepaid/__init__.py
lms_prepaid/api.py
lms_prepaid/lms_prepaid.py
lms_prepaid-0.1.1.dist-info/entry_points.txt
lms_prepaid-0.1.1.dist-info/LICENSE
lms_prepaid-0.1.1.dist-info/WHEEL
lms_prepaid-0.1.1.dist-info/METADATA
lms_prepaid-0.1.1.dist-info/RECORD
